LICENSE
MANIFEST.in
README.md
requirements.txt
setup.cfg
setup.py
django_mp_celery.egg-info/PKG-INFO
django_mp_celery.egg-info/SOURCES.txt
django_mp_celery.egg-info/dependency_links.txt
django_mp_celery.egg-info/requires.txt
django_mp_celery.egg-info/top_level.txt
mpcelery/__init__.py
mpcelery/app.py