Metadata-Version: 1.1
Name: django-mp-celery
Version: 1.0.1
Summary: Django celery app
Home-page: https://github.com/pmaigutyak/mp-celery
Author: Paul Maigutyak
Author-email: pmaigutyak@gmail.com
License: MIT
Download-URL: https://github.com/pmaigutyak/mp-celery/archive/1.0.1.tar.gz
Platform: UNKNOWN
